__init__.py
isloth_python_common_lib/__init__.py
isloth_python_common_lib/constants/General.py
isloth_python_common_lib/constants/__init__.py
isloth_python_common_lib/dtos/ImageProcessorResult.py
isloth_python_common_lib/dtos/ObjectProcessorResult.py
isloth_python_common_lib/dtos/Result.py
isloth_python_common_lib/dtos/__init__.py
isloth_python_common_lib/enums/DetailLevel.py
isloth_python_common_lib/enums/ErrorCode.py
isloth_python_common_lib/enums/PythonEnv.py
isloth_python_common_lib/enums/SortOrder.py
isloth_python_common_lib/enums/StatusCode.py
isloth_python_common_lib/enums/__init__.py
isloth_python_common_lib/errors/AppError.py
isloth_python_common_lib/errors/BadRequestError.py
isloth_python_common_lib/errors/ConflictError.py
isloth_python_common_lib/errors/DatabaseError.py
isloth_python_common_lib/errors/ExternalServiceError.py
isloth_python_common_lib/errors/InternalServerError.py
isloth_python_common_lib/errors/LibraryError.py
isloth_python_common_lib/errors/NotFoundError.py
isloth_python_common_lib/errors/NotImplementedError.py
isloth_python_common_lib/errors/ServiceUnavailableError.py
isloth_python_common_lib/errors/TimeoutError.py
isloth_python_common_lib/errors/UnexpectedError.py
isloth_python_common_lib/errors/__init__.py
isloth_python_common_lib/factories/ProcessorFactory.py
isloth_python_common_lib/factories/__init__.py
isloth_python_common_lib/interfaces/ILogger.py
isloth_python_common_lib/interfaces/IObjectProcessor.py
isloth_python_common_lib/interfaces/__init__.py
isloth_python_common_lib/types/ErrorMessage.py
isloth_python_common_lib/types/ProcessedFile.py
isloth_python_common_lib/types/ServiceConfig.py
isloth_python_common_lib/types/__init__.py
isloth_python_common_lib/types/abstracts/BaseBuilder.py
isloth_python_common_lib/types/abstracts/__init__.py
isloth_python_common_lib/utilities/__init__.py
isloth_python_common_lib/utilities/builders/StringBuilder.py
isloth_python_common_lib/utilities/builders/__init__.py
isloth_python_common_lib-0.9.0.dist-info/licenses/LICENSE
isloth_python_common_lib-0.9.0.dist-info/METADATA
isloth_python_common_lib-0.9.0.dist-info/WHEEL
isloth_python_common_lib-0.9.0.dist-info/top_level.txt
isloth_python_common_lib-0.9.0.dist-info/RECORD
