Metadata-Version: 2.4
Name: isloth-python-common-lib
Version: 0.9.0
Summary: Shared Python library for internal microservices
License: MIT
Requires-Python: >=3.8
License-File: LICENSE
Dynamic: license-file
